[
  { "daf": 2, "date": "January 25, 2023", "mesechta": "nazir" },
  { "daf": 3, "date": "January 26, 2023", "mesechta": "nazir" },
  { "daf": 4, "date": "January 27, 2023", "mesechta": "nazir" },
  { "daf": 5, "date": "January 28, 2023", "mesechta": "nazir" },
  { "daf": 6, "date": "January 29, 2023", "mesechta": "nazir" },
  { "daf": 7, "date": "January 30, 2023", "mesechta": "nazir" },
  { "daf": 8, "date": "January 31, 2023", "mesechta": "nazir" },
  { "daf": 9, "date": "February 1, 2023", "mesechta": "nazir" },
  { "daf": 10, "date": "February 2, 2023", "mesechta": "nazir" },
  { "daf": 11, "date": "February 3, 2023", "mesechta": "nazir" },
  { "daf": 12, "date": "February 4, 2023", "mesechta": "nazir" },
  { "daf": 13, "date": "February 5, 2023", "mesechta": "nazir" },
  { "daf": 14, "date": "February 6, 2023", "mesechta": "nazir" },
  { "daf": 15, "date": "February 7, 2023", "mesechta": "nazir" },
  { "daf": 16, "date": "February 8, 2023", "mesechta": "nazir" },
  { "daf": 17, "date": "February 9, 2023", "mesechta": "nazir" },
  { "daf": 18, "date": "February 10, 2023", "mesechta": "nazir" },
  { "daf": 19, "date": "February 11, 2023", "mesechta": "nazir" },
  { "daf": 20, "date": "February 12, 2023", "mesechta": "nazir" },
  { "daf": 21, "date": "February 13, 2023", "mesechta": "nazir" },
  { "daf": 22, "date": "February 14, 2023", "mesechta": "nazir" },
  { "daf": 23, "date": "February 15, 2023", "mesechta": "nazir" },
  { "daf": 24, "date": "February 16, 2023", "mesechta": "nazir" },
  { "daf": 25, "date": "February 17, 2023", "mesechta": "nazir" },
  { "daf": 26, "date": "February 18, 2023", "mesechta": "nazir" },
  { "daf": 27, "date": "February 19, 2023", "mesechta": "nazir" },
  { "daf": 28, "date": "February 20, 2023", "mesechta": "nazir" },
  { "daf": 29, "date": "February 21, 2023", "mesechta": "nazir" },
  { "daf": 30, "date": "February 22, 2023", "mesechta": "nazir" },
  { "daf": 31, "date": "February 23, 2023", "mesechta": "nazir" },
  { "daf": 32, "date": "February 24, 2023", "mesechta": "nazir" },
  { "daf": 33, "date": "February 25, 2023", "mesechta": "nazir" },
  { "daf": 34, "date": "February 26, 2023", "mesechta": "nazir" },
  { "daf": 35, "date": "February 27, 2023", "mesechta": "nazir" },
  { "daf": 36, "date": "February 28, 2023", "mesechta": "nazir" },
  { "daf": 37, "date": "March 1, 2023", "mesechta": "nazir" },
  { "daf": 38, "date": "March 2, 2023", "mesechta": "nazir" },
  { "daf": 39, "date": "March 3, 2023", "mesechta": "nazir" },
  { "daf": 40, "date": "March 4, 2023", "mesechta": "nazir" },
  { "daf": 41, "date": "March 5, 2023", "mesechta": "nazir" },
  { "daf": 42, "date": "March 6, 2023", "mesechta": "nazir" },
  { "daf": 43, "date": "March 7, 2023", "mesechta": "nazir" },
  { "daf": 44, "date": "March 8, 2023", "mesechta": "nazir" },
  { "daf": 45, "date": "March 9, 2023", "mesechta": "nazir" },
  { "daf": 46, "date": "March 10, 2023", "mesechta": "nazir" },
  { "daf": 47, "date": "March 11, 2023", "mesechta": "nazir" },
  { "daf": 48, "date": "March 12, 2023", "mesechta": "nazir" },
  { "daf": 49, "date": "March 13, 2023", "mesechta": "nazir" },
  { "daf": 50, "date": "March 14, 2023", "mesechta": "nazir" },
  { "daf": 51, "date": "March 15, 2023", "mesechta": "nazir" },
  { "daf": 52, "date": "March 16, 2023", "mesechta": "nazir" },
  { "daf": 53, "date": "March 17, 2023", "mesechta": "nazir" },
  { "daf": 54, "date": "March 18, 2023", "mesechta": "nazir" },
  { "daf": 55, "date": "March 19, 2023", "mesechta": "nazir" },
  { "daf": 56, "date": "March 20, 2023", "mesechta": "nazir" },
  { "daf": 57, "date": "March 21, 2023", "mesechta": "nazir" },
  { "daf": 58, "date": "March 22, 2023", "mesechta": "nazir" },
  { "daf": 59, "date": "March 23, 2023", "mesechta": "nazir" },
  { "daf": 60, "date": "March 24, 2023", "mesechta": "nazir" },
  { "daf": 61, "date": "March 25, 2023", "mesechta": "nazir" },
  { "daf": 62, "date": "March 26, 2023", "mesechta": "nazir" },
  { "daf": 63, "date": "March 27, 2023", "mesechta": "nazir" },
  { "daf": 64, "date": "March 28, 2023", "mesechta": "nazir" },
  { "daf": 65, "date": "March 29, 2023", "mesechta": "nazir" },
  { "daf": 66, "date": "March 30, 2023", "mesechta": "nazir" }
]
